torch_persistency/__init__.py
torch_persistency/ModulePersistency.py
torch_model_persistency-0.1.6.dist-info/LICENSE
torch_model_persistency-0.1.6.dist-info/WHEEL
torch_model_persistency-0.1.6.dist-info/METADATA
torch_model_persistency-0.1.6.dist-info/RECORD
